<?xml version="1.0" encoding="utf-8" ?>
<dwsync>
<file name="vimeo.min.js" server="ftp.freehostia.com/g1gbo.uk/" local="131526508720000000" remote="131761095000000000" Dst="2" />
<file name="vimeo.js" server="ftp.freehostia.com/g1gbo.uk/" local="131526508720000000" remote="131761095000000000" Dst="2" />
<file name="twitch.min.js" server="ftp.freehostia.com/g1gbo.uk/" local="131526508720000000" remote="131761095000000000" Dst="2" />
<file name="twitch.js" server="ftp.freehostia.com/g1gbo.uk/" local="131526508720000000" remote="131761095000000000" Dst="2" />
<file name="soundcloud.min.js" server="ftp.freehostia.com/g1gbo.uk/" local="131469924440000000" remote="131761095000000000" Dst="2" />
<file name="soundcloud.js" server="ftp.freehostia.com/g1gbo.uk/" local="131469924440000000" remote="131761095000000000" Dst="2" />
<file name="facebook.min.js" server="ftp.freehostia.com/g1gbo.uk/" local="131526508720000000" remote="131761095000000000" Dst="2" />
<file name="facebook.js" server="ftp.freehostia.com/g1gbo.uk/" local="131526508720000000" remote="131761095000000000" Dst="2" />
<file name="dailymotion.min.js" server="ftp.freehostia.com/g1gbo.uk/" local="131526508720000000" remote="131761095000000000" Dst="2" />
<file name="dailymotion.js" server="ftp.freehostia.com/g1gbo.uk/" local="131526508720000000" remote="131761095000000000" Dst="2" />
</dwsync>